CHANGES.txt
README.txt
TODO.txt
bootstrap.py
buildout.cfg
setup.py
src/gocept/__init__.py
src/gocept.zope3instance.egg-info/PKG-INFO
src/gocept.zope3instance.egg-info/SOURCES.txt
src/gocept.zope3instance.egg-info/dependency_links.txt
src/gocept.zope3instance.egg-info/entry_points.txt
src/gocept.zope3instance.egg-info/namespace_packages.txt
src/gocept.zope3instance.egg-info/not-zip-safe
src/gocept.zope3instance.egg-info/requires.txt
src/gocept.zope3instance.egg-info/top_level.txt
src/gocept/zope3instance/README.txt
src/gocept/zope3instance/__init__.py
src/gocept/zope3instance/ctl.py
src/gocept/zope3instance/experiments.txt
src/gocept/zope3instance/tests.py
src/gocept/zope3instance/zope3scripts.py
src/gocept/zope3instance/skel/base.zcml
src/gocept/zope3instance/skel/ftesting.zcml
src/gocept/zope3instance/skel/principals-testing.zcml
src/gocept/zope3instance/skel/principals.zcml.in
src/gocept/zope3instance/skel/securitypolicy.zcml
src/gocept/zope3instance/skel/site.zcml
src/gocept/zope3instance/skel/zdaemon.conf.in
src/gocept/zope3instance/skel/zope.conf.in
