Metadata-Version: 1.0
Name: gocept.zope3instance
Version: 2.0a2
Summary: zc.buildout recipe for defining a Zope 3 instance
Home-page: http://svn.zope.org/gocept.zope3instance
Author: Christian Theune
Author-email: ct@gocept.com
License: ZPL 2.1
Keywords: zope3 buildout
Platform: UNKNOWN
Classifier: Framework :: Buildout
